{
  "subtitle": "", 
  "description": "Chagua jibu: [NDIO] au [HAPANA] ", 
  "language": "swa_TZ", 
  "title": "Je virusi vya Ukimwi (VVU) na  UKIMWI ni kitu kimoja?", 
  "primary_category": "8c345443605d41529bec28a877bcadca", 
  "created_at": "2015-10-08T09:44:38.470707+00:00", 
  "featured_in_category": false, 
  "modified_at": "2015-10-08T09:44:38.471039+00:00", 
  "_version": {
    "package_version": "1.4.3", 
    "language_version": "2.7.6", 
    "language_version_string": "2.7.6 (default, Jun 22 2015, 18:01:27) \n[GCC 4.8.2]", 
    "language": "python", 
    "package": "elastic-git"
  }, 
  "linked_pages": [], 
  "id": null, 
  "content": "HAPANA. sio kitu kimoja na UKIMWI. VVU ni kifupisho cha maneno: Virusi vya UKIMWI. VVU hushambulia mfumo wa kinga ya mwiliambao hupambana na magonjwa . Bila matibabu, VVU vinaweza kusababisha UKIMWI, ambao ni vifupisho vya maneno Ukosefu wa Kinga Mwilini. VVU huambikizwa kwa njia kuu tano kupitia majimaji ya mwili: \r\n\r\n 1. Damu \r\n 2. shahawa, \r\n 3. majimaji ya ukeni, \r\n 4. majimaji kutoka kwenye njia ya haja kubwa na\r\n 5. maziwa ya mama.\r\nMara mtu anapofikia kuwa na UKIMWI, miili yao inakuwa na wakati mgumu sana wa  kupambana na magonjwa mengine. Hii  ndio sababu  watu wanakufa kutokana na magonjwa yanayohusiana na UKIMWI, lakini si UKIMWI wenyewe.\r\n\r\nMASWALI YANAYOFUATANA:\r\n\r\n", 
  "source": null, 
  "featured": false, 
  "author_tags": [], 
  "image": null, 
  "published": null, 
  "position": 0, 
  "image_host": "http://thumbor.unicore.io", 
  "slug": "je-virusi-vya-ukimwi-vvu-na-ukimwi-ni-kitu-kimoja", 
  "uuid": "54269935f51a41798f427aa501f7538a"
}