{
  "subtitle": "", 
  "description": "Jifunze zaidi kuhusu ALL IN", 
  "language": "swa_TZ", 
  "title": "Mapenzi, mahusiano, ngono, VVU na maswali mengine magumu", 
  "primary_category": "6f350edccd954099a9929cb366e97cc5", 
  "created_at": "2015-10-08T09:51:37+00:00", 
  "featured_in_category": true, 
  "modified_at": "2016-08-25T07:27:50.457550+00:00", 
  "_version": {
    "package_version": "1.4.3", 
    "language_version": "2.7.6", 
    "language": "python", 
    "language_version_string": "2.7.6 (default, Jun 22 2015, 18:01:27) \n[GCC 4.8.2]", 
    "package": "elastic-git"
  }, 
  "linked_pages": [], 
  "id": null, 
  "content": "Kuhusu mahusiano, ngono, ujinsia, mimba, VVU na magonjwa ya zinaa, ALL IN inasaidia katika kukabiliana na masuala magumu yanayohusu maisha ya kila siku. Iliundwa kwa ajili ya vijana balelehe kwa na  vijana balehe, sisi hutoa ukweli moja kwa moja na habari za kuaminika.\r\n\r\nTukijua zaidi kuhusu afya zetu itatuwezesha kufanya maamuzi yetu wenyewe na kuwa katika udhibiti. ALL IN ni kuhusu kuchukua hatua. Ni kuhusu kukomesha VVU na UKIMWI. Ni kuhusu kuishi maisha kwa ukamilifu. \r\n\r\nMada inayofuata\r\n", 
  "source": null, 
  "featured": false, 
  "author_tags": [], 
  "image": null, 
  "published": null, 
  "position": 0, 
  "image_host": "http://thumbor.unicore.io", 
  "slug": "mapenzi-mahusiano-ngono-VVU-na-maswali-mengine-magumu", 
  "uuid": "70289cab702846d3880d82181dfdfa3b"
}